pypvr.py
pypvr-1.0.0.dist-info/licenses/LICENSE.txt
pypvr-1.0.0.dist-info/METADATA
pypvr-1.0.0.dist-info/WHEEL
pypvr-1.0.0.dist-info/top_level.txt
pypvr-1.0.0.dist-info/RECORD
