Metadata-Version: 2.4
Name: PyPVR
Version: 1.0.0
Summary: PyPVR is an unofficial, modern tool written in Python for encoding / decoding PowerVR2 images used by SEGA Dreamcast and SEGA Naomi.
Home-page: https://github.com/VincentNLOBJ/PyPVR
Author: VincentNL
Author-email: VincentNL <zgoro@protonmail.com>
Project-URL: Homepage, https://github.com/VincentNLOBJ/PyPVR
Project-URL: Issues, https://github.com/VincentNLOBJ/PyPVR/issues
Classifier: Programming Language :: Python :: 3
Classifier: License :: OSI Approved :: MIT License
Classifier: Operating System :: OS Independent
Requires-Python: >=3.9
License-File: LICENSE.txt
Dynamic: author
Dynamic: home-page
Dynamic: license-file
Dynamic: requires-python
